pyValEIA/__init__.py
pyValEIA/eia/__init__.py
pyValEIA/eia/detection.py
pyValEIA/eia/types.py
pyValEIA/io/__init__.py
pyValEIA/io/download.py
pyValEIA/io/load.py
pyValEIA/io/write.py
pyValEIA/plots/__init__.py
pyValEIA/plots/mad_diagnostic_plots.py
pyValEIA/plots/mad_stat_plots.py
pyValEIA/plots/swarm_diagnostic_plots.py
pyValEIA/plots/swarm_stat_plots.py
pyValEIA/plots/utils.py
pyValEIA/stats/__init__.py
pyValEIA/stats/skill_score.py
pyValEIA/stats/tables.py
pyValEIA/tests/__init__.py
pyValEIA/tests/test_utils_coords.py
pyValEIA/utils/__init__.py
pyValEIA/utils/clean.py
pyValEIA/utils/conjunctions.py
pyValEIA/utils/coords.py
pyValEIA/utils/filters.py
pyValEIA/utils/math.py
pyvaleia-0.0.2.dist-info/licenses/LICENSE
pyvaleia-0.0.2.dist-info/METADATA
pyvaleia-0.0.2.dist-info/WHEEL
pyvaleia-0.0.2.dist-info/top_level.txt
pyvaleia-0.0.2.dist-info/RECORD
