Metadata-Version: 2.4
Name: pyValEIA
Version: 0.0.2
Summary: Validation tools for the Equatorial Ionization Anomally
Home-page: https://github.com/aburrell/pyValEIA
Author-email: Angeline Burrell <angeline.g.burrell.civ@us.navy.mil>
License:                   GNU LESSER GENERAL PUBLIC LICENSE
Project-URL: Source, https://github.com/aburrell/pyValEIA
Project-URL: Tracker, https://github.com/aburrell/pyValEIA/issues
Project-URL: Download, https://github.com/aburrell/pyValEIA/releases
Keywords: validation,ionosphere,EIA,equatorial ionization anomally,equatorial ionisation anomally,heliophysics
Classifier: Development Status :: 3 - Alpha
Classifier: Topic :: Scientific/Engineering :: Physics
Classifier: Topic :: Scientific/Engineering :: Atmospheric Science
Classifier: Intended Audience :: Science/Research
Classifier: License :: OSI Approved :: GNU Lesser General Public License v3 (LGPLv3)
Classifier: Natural Language :: English
Classifier: Programming Language :: Python :: 3
Classifier: Programming Language :: Python :: 3.10
Classifier: Programming Language :: Python :: 3.11
Classifier: Programming Language :: Python :: 3.12
Classifier: Programming Language :: Python :: 3.13
Classifier: Operating System :: POSIX :: Linux
Classifier: Operating System :: MacOS :: MacOS X
Classifier: Operating System :: Microsoft :: Windows
Requires-Python: >=3.10
License-File: LICENSE
Requires-Dist: apexpy
Requires-Dist: cartopy
Requires-Dist: cdflib
Requires-Dist: matplotlib
Requires-Dist: netCDF4
Requires-Dist: numpy
Requires-Dist: pandas
Requires-Dist: pydarn
Requires-Dist: PyIRI
Requires-Dist: pysat
Requires-Dist: pysatMadrigal
Requires-Dist: requests
Requires-Dist: scipy
Provides-Extra: test
Requires-Dist: coverage[toml]; extra == "test"
Requires-Dist: flake8; extra == "test"
Requires-Dist: flake8-docstrings; extra == "test"
Provides-Extra: doc
Requires-Dist: myst_parser; extra == "doc"
Requires-Dist: numpydoc; extra == "doc"
Requires-Dist: pyproject_parser; extra == "doc"
Requires-Dist: sphinx; extra == "doc"
Requires-Dist: sphinx-autoapi; extra == "doc"
Requires-Dist: sphinx-rtd-theme; extra == "doc"
Dynamic: license-file
